converso/__init__.py
converso/conversational_engine/__init__.py
converso/conversational_engine/form_agent/__init__.py
converso/conversational_engine/form_agent/form_agent_executor.py
converso/conversational_engine/form_agent/form_tool.py
converso/conversational_engine/form_agent/form_tool_executor.py
converso/conversational_engine/form_agent/model_factory.py
converso-0.2.0.dist-info/METADATA
converso-0.2.0.dist-info/WHEEL
converso-0.2.0.dist-info/RECORD
